xtquant/__init__.py
xtquant/config/captial_structure_1.ini
xtquant/config/cashflow_new_1.ini
xtquant/config/config.lua
xtquant/config/configHelper.lua
xtquant/config/env.lua
xtquant/config/MarketTime.ini
xtquant/config/metaInfo.json
xtquant/config/pershare_new.ini
xtquant/config/sharebalance_new_1.ini
xtquant/config/shareholder_new_1.ini
xtquant/config/shareincome_new_1.ini
xtquant/config/table2json.lua
xtquant/config/top10holder_new_1.ini
xtquant/config/tradeTime.txt
xtquant/config/xtquantservice.log4cxx
xtquant/config/xtquantservice.lua
xtquant/config/xtquoterconfig.xml
xtquant/config/xtstocktype.lua
xtquant/datacenter.cp310-win_amd64.pyd
xtquant/datacenter.cp311-win_amd64.pyd
xtquant/datacenter.cp36-win_amd64.pyd
xtquant/datacenter.cp37-win_amd64.pyd
xtquant/datacenter.cp38-win_amd64.pyd
xtquant/datacenter.cp39-win_amd64.pyd
xtquant/doc/xtdata.md
xtquant/doc/xttrader.md
xtquant/libeay32.dll
xtquant/log4cxx.dll
xtquant/msvcp140.dll
xtquant/py.typed
xtquant/qmttools/__init__.py
xtquant/qmttools/contextinfo.py
xtquant/qmttools/functions.py
xtquant/qmttools/stgentry.py
xtquant/qmttools/stgframe.py
xtquant/ssleay32.dll
xtquant/vcruntime140.dll
xtquant/xtbson/__init__.py
xtquant/xtbson/bson36/__init__.py
xtquant/xtbson/bson36/_cbson.cp36-win_amd64.pyd
xtquant/xtbson/bson36/_helpers.py
xtquant/xtbson/bson36/binary.py
xtquant/xtbson/bson36/code.py
xtquant/xtbson/bson36/codec_options.py
xtquant/xtbson/bson36/dbref.py
xtquant/xtbson/bson36/decimal128.py
xtquant/xtbson/bson36/errors.py
xtquant/xtbson/bson36/int64.py
xtquant/xtbson/bson36/json_util.py
xtquant/xtbson/bson36/max_key.py
xtquant/xtbson/bson36/min_key.py
xtquant/xtbson/bson36/objectid.py
xtquant/xtbson/bson36/raw_bson.py
xtquant/xtbson/bson36/regex.py
xtquant/xtbson/bson36/son.py
xtquant/xtbson/bson36/timestamp.py
xtquant/xtbson/bson36/tz_util.py
xtquant/xtbson/bson37/__init__.py
xtquant/xtbson/bson37/_cbson.cp310-win_amd64.pyd
xtquant/xtbson/bson37/_cbson.cp311-win_amd64.pyd
miniqmt_xtquant-20240329.dist-info/METADATA
miniqmt_xtquant-20240329.dist-info/WHEEL
miniqmt_xtquant-20240329.dist-info/RECORD
