Metadata-Version: 2.1
Name: miniqmt_xtquant
Version: 20240329
Summary: mini QMT工具
Home-page: https://dict.thinktrader.net/nativeApi/download_xtquant.html
License: MIT
Keywords: quant,tools,qmt
Author: thinktrader
Requires-Python: >=3.8,<4.0
Classifier: License :: OSI Approved :: MIT License
Classifier: Programming Language :: Python
Classifier: Programming Language :: Python :: 3
Classifier: Programming Language :: Python :: 3.8
Classifier: Programming Language :: Python :: 3.9
Classifier: Programming Language :: Python :: 3.10
Classifier: Programming Language :: Python :: 3.11
Classifier: Programming Language :: Python :: 3.12
Classifier: Programming Language :: Python :: 3.13
Classifier: Programming Language :: Python :: Implementation :: CPython
Classifier: Programming Language :: Python :: Implementation :: PyPy
